inflow/__init__.py
inflow/client.py
inflow/connection.py
inflow/exceptions.py
inflow/measurement.py
inflow/session.py
inflow/utils.py
inflow/write.py
inflow-0.3.2.dist-info/LICENSE
inflow-0.3.2.dist-info/METADATA
inflow-0.3.2.dist-info/WHEEL
inflow-0.3.2.dist-info/top_level.txt
inflow-0.3.2.dist-info/RECORD
