Metadata-Version: 2.1
Name: inflow
Version: 0.3.2
Summary: A simple InfluxDB client library.
Home-page: https://github.com/AdvancedClimateSystems/inflow/
Author: Jaap Broekhuizen
Author-email: broekhuizen@baopt.nl
License: MPL
Platform: UNKNOWN
Classifier: Intended Audience :: Developers
Classifier: License :: OSI Approved :: Mozilla Public License 2.0 (MPL 2.0)
Classifier: Operating System :: OS Independent
Classifier: Programming Language :: Python :: 2
Classifier: Programming Language :: Python :: 3
Requires-Dist: requests (~=2.11)
Requires-Dist: six (~=1.11)
Requires-Dist: pytz
